{
    "MA": {
        "count": 0,
        "classes": [
            "http://www.w3.org/2002/07/owl#Nothing"
        ]
    },
    "PO": {
        "count": 0,
        "classes": [
            "http://www.w3.org/2002/07/owl#Nothing"
        ]
    },
    "DDANAT": {
        "count": 0,
        "classes": [
            "http://www.w3.org/2002/07/owl#Nothing"
        ]
    },
    "MO": {
        "count": 0,
        "classes": [
            "http://www.w3.org/2002/07/owl#Nothing"
        ]
    },
    "GO": {
        "count": 0,
        "classes": [
            "http://www.w3.org/2002/07/owl#Nothing"
        ]
    }
}